ServeIt-0.0.9.dist-info/DESCRIPTION.rst
ServeIt-0.0.9.dist-info/METADATA
ServeIt-0.0.9.dist-info/RECORD
ServeIt-0.0.9.dist-info/WHEEL
ServeIt-0.0.9.dist-info/metadata.json
ServeIt-0.0.9.dist-info/top_level.txt
serveit/__init__.py
serveit/config.py
serveit/log_utils.py
serveit/prediction_server.py
serveit/server.py
serveit/sklearn_server.py
serveit/utils.py
serveit/wsgi.py
tests/keras/__init__.py
tests/keras/test_prediction_server.py
tests/keras/test_server.py
tests/pytorch/__init__.py
tests/pytorch/test_server.py
tests/sklearn/__init__.py
tests/sklearn/test_prediction_server.py
tests/sklearn/test_server.py
tests/sklearn/test_sklearn_server.py
