Metadata-Version: 2.0
Name: ServeIt
Version: 0.0.9
Summary: Machine learning prediction serving
Home-page: https://github.com/rtlee9/serveit
Author: Ryan Lee
Author-email: ryantlee9@gmail.com
License: UNKNOWN
Keywords: machine learning model deployment serving API RESTful
Platform: UNKNOWN
Classifier: Development Status :: 3 - Alpha
Classifier: Intended Audience :: Developers
Classifier: Topic :: Software Development :: Build Tools
Classifier: Topic :: Scientific/Engineering :: Artificial Intelligence
Classifier: Topic :: Internet :: WWW/HTTP :: WSGI :: Server
Classifier: License :: OSI Approved :: MIT License
Classifier: Programming Language :: Python :: 2.7
Classifier: Programming Language :: Python :: 3.6
Classifier: Programming Language :: Python :: 3.7
Requires-Dist: flask
Requires-Dist: flask-restful
Requires-Dist: meinheld
Provides-Extra: dev
Requires-Dist: check-manifest; extra == 'dev'
Provides-Extra: test
Requires-Dist: coverage; extra == 'test'
